[
    {
        "id": 1,
        "purpose": "Website Domain",
        "amount": 1278.9,
        "date": "2025-08-17",
        "type": "Digital",
        "persons": [
            "Wasi"
        ],
        "comments": "Cloudflare domain registration for the official website. 10.44$*122.5=1278.9$",
        "receipts": [
            {
                "url": "./receipts/cloudflare_receipt.jpg?v=1755951855887",
                "filename": "cloudflare_receipt.jpg",
                "description": "Cloudflare Domain Purchase"
            },
            {
                "url": "./receipts/ebl_exchange_rage.jpg?v=1755951863836",
                "filename": "ebl_exchange_rage.jpg",
                "description": "Exchange rate of EBL Card"
            }
        ]
    },
    {
        "id": 1755775346147,
        "purpose": "Advance Payment to Print House",
        "amount": 2000,
        "date": "2025-08-21",
        "type": "Printing",
        "persons": [
            "Wasi",
            "Shezan"
        ],
        "comments": "",
        "receipts": [
            {
                "url": "./receipts/print_house_1.jpg?v=1755949726095",
                "filename": "print_house_1.jpg",
                "description": "Voucher"
            }
        ]
    },
    {
        "id": 1755881362231,
        "purpose": "Facebook Page Boost",
        "amount": 234.23,
        "date": "2025-08-22",
        "type": "Digital",
        "persons": [
            "Wasi"
        ],
        "comments": "Boost the page to gain more followers",
        "receipts": [
            {
                "description": "Invoice",
                "filename": "facebook_boost_1_jpg.jpg",
                "url": "./receipts/facebook_boost_1_jpg.jpg?v=1755949816324"
            }
        ]
    },
    {
        "id": 1755946461803,
        "purpose": "Advance Payment to Print House",
        "amount": 8000,
        "date": "2025-08-23",
        "type": "Printing",
        "persons": [
            "Wasi",
            "Shezan"
        ],
        "comments": "",
        "receipts": [
            {
                "url": "./receipts/print_house_2.jpg?v=1755953317304",
                "filename": "print_house_2.jpg",
                "description": "Money Receipt"
            }
        ]
    },
    {
        "id": 1757749087726,
        "purpose": "Reels of Wedding Banner shoot advance",
        "amount": 4000,
        "date": "2025-09-13",
        "type": "Camera",
        "persons": [
            "Wasi",
            "Shezan",
            "Minhaz",
            "Nafiz",
            "Anam"
        ],
        "comments": "For banner shoot",
        "receipts": [
            {
                "url": "./receipts/reels_of_wedding-1757852171039.jpeg",
                "filename": "reels_of_wedding-1757852171039.jpeg",
                "description": "Voucher"
            }
        ]
    }
]